jobrunner/__init__.py
jobrunner/argparse.py
jobrunner/binutils.py
jobrunner/compat.py
jobrunner/config.py
jobrunner/info.py
jobrunner/logging.py
jobrunner/main.py
jobrunner/plugins.py
jobrunner/utils.py
jobrunner/db/__init__.py
jobrunner/db/sqlite_db.py
jobrunner/mail/__init__.py
jobrunner/mail/chat.py
jobrunner/plugin/__init__.py
jobrunner/service/__init__.py
jobrunner/service/registry.py
shell_jobrunner-2.7.1.dist-info/licenses/LICENSE
shell_jobrunner-2.7.1.dist-info/METADATA
shell_jobrunner-2.7.1.dist-info/WHEEL
shell_jobrunner-2.7.1.dist-info/entry_points.txt
shell_jobrunner-2.7.1.dist-info/top_level.txt
shell_jobrunner-2.7.1.dist-info/RECORD
