Metadata-Version: 2.4
Name: shell-jobrunner
Version: 2.7.1
Summary: Shell-based job runner with logging
Home-page: https://github.com/wwade/jobrunner
Project-URL: Source, https://github.com/wwade/jobrunner
Classifier: Intended Audience :: End Users/Desktop
Classifier: License :: OSI Approved :: GNU General Public License v3 (GPLv3)
Classifier: Natural Language :: English
Classifier: Development Status :: 5 - Production/Stable
Classifier: Environment :: Console
Classifier: Operating System :: MacOS
Classifier: Operating System :: POSIX
Classifier: Operating System :: POSIX :: Linux
Classifier: Programming Language :: Python
Classifier: Programming Language :: Python :: 3
Classifier: Programming Language :: Python :: 3.9
Classifier: Programming Language :: Python :: 3.10
Classifier: Programming Language :: Python :: 3.11
Classifier: Programming Language :: Python :: 3.12
Classifier: Topic :: Utilities
Classifier: Topic :: Terminals
Classifier: Topic :: System :: Shells
Requires-Python: >=3.9
License-File: LICENSE
Requires-Dist: chardet
Requires-Dist: dateutils
Requires-Dist: requests
Requires-Dist: six
Dynamic: license-file
